invutil/__init__.py
invutil/config.py
invutil/date_utils.py
invutil/helpers.py
invutil/logger.py
invutil/numeric_utils.py
invutil-0.1.1.dist-info/LICENSE
invutil-0.1.1.dist-info/METADATA
invutil-0.1.1.dist-info/WHEEL
invutil-0.1.1.dist-info/RECORD
