Metadata-Version: 2.3
Name: invutil
Version: 0.1.1
Summary: Utility functions for financial document processing
Author: Tom Sapletta
Requires-Python: >=3.8,<4.0
Classifier: Programming Language :: Python :: 3
Classifier: Programming Language :: Python :: 3.8
Classifier: Programming Language :: Python :: 3.9
Classifier: Programming Language :: Python :: 3.10
Classifier: Programming Language :: Python :: 3.11
Classifier: Programming Language :: Python :: 3.12
Classifier: Programming Language :: Python :: 3.13
Requires-Dist: PyYAML (>=6.0,<7.0)
Requires-Dist: click (>=8.0.0,<9.0.0)
Requires-Dist: pydantic (>=2.0.0,<3.0.0)
